common_inspection_py/__init__.py
common_inspection_py/config/__init__.py
common_inspection_py/config/datamodels.py
common_inspection_py/interfaces/__init__.py
common_inspection_py/interfaces/datarequests.py
common_inspection_py/interfaces/requests.py
common_inspection_py/interfaces/task.py
common_inspection_py/types/__init__.py
common_inspection_py/types/tasks.py
common_inspection_py/utils/__init__.py
common_inspection_py/utils/s3_helper.py
common_inspection_py-0.0.8.dist-info/METADATA
common_inspection_py-0.0.8.dist-info/WHEEL
common_inspection_py-0.0.8.dist-info/top_level.txt
common_inspection_py-0.0.8.dist-info/RECORD
